harserver/__init__.py
har_server-0.0.1.dist-info/LICENSE
har_server-0.0.1.dist-info/METADATA
har_server-0.0.1.dist-info/WHEEL
har_server-0.0.1.dist-info/top_level.txt
har_server-0.0.1.dist-info/RECORD
