Metadata-Version: 2.1
Name: har-server
Version: 0.0.1
Summary: Programmable HTTP server for testing
Home-page: https://github.com/dave-shawley/har-server
Author: Dave Shawley
Author-email: daveshawley+harserver@gmail.com
License: UNKNOWN
Project-URL: Builds, https://circleci.com/gh/dave-shawley/har-server/
Project-URL: Coverage Reports, https://coveralls.io/github/dave-shawley/har-server
Project-URL: Documentation, http://har-server.readthedocs.io/
Project-URL: Source Code, https://github.com/dave-shawley/har-server/
Platform: UNKNOWN
Classifier: Development Status :: 1 - Planning
Classifier: Environment :: No Input/Output (Daemon)
Classifier: Framework :: AsyncIO
Classifier: Intended Audience :: Developers
Classifier: License :: OSI Approved :: BSD License
Classifier: Natural Language :: English
Classifier: Operating System :: POSIX
Classifier: Programming Language :: Python :: 3 :: Only
Classifier: Programming Language :: Python :: 3.7
Classifier: Topic :: Internet :: WWW/HTTP :: HTTP Servers
Classifier: Topic :: Software Development :: Testing :: Mocking
Requires-Dist: aiohttp (==3.4.4)
Requires-Dist: yarl (==1.3.0)
Provides-Extra: dev
Requires-Dist: coverage (==4.5.2) ; extra == 'dev'
Requires-Dist: coveralls (==1.5.1) ; extra == 'dev'
Requires-Dist: flake8 (==3.6.0) ; extra == 'dev'
Requires-Dist: nose (==1.3.7) ; extra == 'dev'
Requires-Dist: pycodestyle (==2.4.0) ; extra == 'dev'
Requires-Dist: pyflakes (==2.0.0) ; extra == 'dev'
Requires-Dist: Sphinx (==1.8.2) ; extra == 'dev'
Requires-Dist: twine (==1.12.1) ; extra == 'dev'
Requires-Dist: wheel (==0.32.3) ; extra == 'dev'
Requires-Dist: yapf (==0.25.0) ; extra == 'dev'
Provides-Extra: docs
Requires-Dist: Sphinx (==1.8.2) ; extra == 'docs'
